napari_melt_pool_tracker/__init__.py
napari_melt_pool_tracker/_reader.py
napari_melt_pool_tracker/_sample_data.py
napari_melt_pool_tracker/_utils.py
napari_melt_pool_tracker/_version.py
napari_melt_pool_tracker/_widget.py
napari_melt_pool_tracker/napari.yaml
napari_melt_pool_tracker/_tests/__init__.py
napari_melt_pool_tracker/_tests/test_reader.py
napari_melt_pool_tracker/_tests/test_sample_data.py
napari_melt_pool_tracker/_tests/test_utils.py
napari_melt_pool_tracker/_tests/test_widget.py
napari_melt_pool_tracker/data/__init__.py
napari_melt_pool_tracker/data/wall1_H5.tif
napari_melt_pool_tracker-0.1.3.dist-info/LICENSE
napari_melt_pool_tracker-0.1.3.dist-info/METADATA
napari_melt_pool_tracker-0.1.3.dist-info/WHEEL
napari_melt_pool_tracker-0.1.3.dist-info/entry_points.txt
napari_melt_pool_tracker-0.1.3.dist-info/top_level.txt
napari_melt_pool_tracker-0.1.3.dist-info/RECORD
