Metadata-Version: 2.2
Name: napari-melt-pool-tracker
Version: 0.1.3
Summary: Plugin for tracking the width and depth of the melt pool and keyhole in x-ray images of laser powder bed fusion experiments.
Home-page: https://github.com/EPFL-Center-for-Imaging/napari-melt-pool-tracker
Author: Florian Aymanns
Author-email: florian.aymanns@epfl.ch
License: BSD-3-Clause
Classifier: Development Status :: 2 - Pre-Alpha
Classifier: Framework :: napari
Classifier: Intended Audience :: Developers
Classifier: License :: OSI Approved :: BSD License
Classifier: Operating System :: OS Independent
Classifier: Programming Language :: Python
Classifier: Programming Language :: Python :: 3
Classifier: Programming Language :: Python :: 3 :: Only
Classifier: Programming Language :: Python :: 3.8
Classifier: Programming Language :: Python :: 3.9
Classifier: Programming Language :: Python :: 3.10
Classifier: Topic :: Scientific/Engineering :: Image Processing
Requires-Python: >=3.8
License-File: LICENSE
Requires-Dist: numpy
Requires-Dist: magicgui
Requires-Dist: qtpy
Requires-Dist: h5py
Requires-Dist: napari-cursor-tracker
Requires-Dist: napari
Requires-Dist: pandas
Requires-Dist: scikit-image
Requires-Dist: tifffile
Requires-Dist: scipy
Provides-Extra: testing
Requires-Dist: tox; extra == "testing"
Requires-Dist: pytest; extra == "testing"
Requires-Dist: pytest-cov; extra == "testing"
Requires-Dist: pytest-qt; extra == "testing"
Requires-Dist: napari; extra == "testing"
Requires-Dist: pyqt5; extra == "testing"
